MANIFEST.in
README.md
setup.cfg
setup.py
etc/gcp/gpu_1xk80.yaml
etc/gcp/gpu_1xv100.yaml
etc/gcp/gpu_1xv100_highmem.yaml
etc/gcp/gpu_4xk80.yaml
etc/gcp/gpu_4xv100.yaml
etc/gcp/gpu_8xk80.yaml
etc/gcp/gpu_8xv100.yaml
etc/gcp/standard.yaml
etc/isprs_benchmark_example/predict_isprs.yaml
etc/isprs_benchmark_example/train_isprs.yaml
etc/usecases/s2-forestry/predic_s2_forestry.yaml
etc/usecases/s2-forestry/train_s2_forestry.yaml
src/hugin/__init__.py
src/hugin.egg-info/PKG-INFO
src/hugin.egg-info/SOURCES.txt
src/hugin.egg-info/dependency_links.txt
src/hugin.egg-info/entry_points.txt
src/hugin.egg-info/not-zip-safe
src/hugin.egg-info/requires.txt
src/hugin.egg-info/top_level.txt
src/hugin/_data/__init__.py
src/hugin/_data/logging-config.yaml
src/hugin/engine/__init__.py
src/hugin/engine/core.py
src/hugin/engine/keras.py
src/hugin/engine/scene.py
src/hugin/io/__init__.py
src/hugin/io/dataset_loaders.py
src/hugin/io/loader.py
src/hugin/models/__init__.py
src/hugin/models/unet/__init__.py
src/hugin/models/unet/unetv14.py
src/hugin/postprocessing/__init__.py
src/hugin/postprocessing/pixelwise.py
src/hugin/preprocessing/__init__.py
src/hugin/preprocessing/augmentation.py
src/hugin/preprocessing/nadir_tools.py
src/hugin/preprocessing/rasterize.py
src/hugin/preprocessing/standardize.py
src/hugin/tools/IOUtils.py
src/hugin/tools/__init__.py
src/hugin/tools/callbacks.py
src/hugin/tools/cli.py
src/hugin/tools/loss.py
src/hugin/tools/predict.py
src/hugin/tools/train.py
src/hugin/tools/utils.py
src/hugin/tools/vectorize.py