Metadata-Version: 2.1
Name: hugin
Version: 0.2.0
Summary: HuginEO - Machine Learning for Earth Observation experimentation tool
Home-page: https://github.com/sage-group/hugin
Author: Marian Neagul
Author-email: mneagul@gmail.com
License: apache-2.0
Keywords: deep learning,machine learning,earth observation
Platform: UNKNOWN
Classifier: Development Status :: 3 - Alpha
Classifier: Environment :: Console
Classifier: Intended Audience :: Science/Research
Classifier: License :: OSI Approved :: Apache Software License
Classifier: Programming Language :: Python :: 3
Classifier: Topic :: Scientific/Engineering :: Image Recognition
Classifier: Topic :: Scientific/Engineering :: GIS
Classifier: Topic :: Scientific/Engineering :: Artificial Intelligence
Requires-Python: >=3.6
Provides-Extra: hugin_data_augmentation
